<?xml version="1.0" encoding="utf-8" ?>
<Defs>

	<ThingDef Name="O21BaseMakeableGunMedieval" ParentName="BaseMakeableGun" Abstract="True">
        <recipeMaker>
            <workSpeedStat>GeneralLaborSpeed</workSpeedStat>
            <workSkill>Crafting</workSkill>
            <effectWorking>Smith</effectWorking>
            <soundWorking>Recipe_Smith</soundWorking>
            <recipeUsers>
                <li>ElectricSmithy</li>
                <li>FueledSmithy</li>
            </recipeUsers>
            <unfinishedThingDef>UnfinishedGun</unfinishedThingDef>
            <researchPrerequisite>O21_MedievalGunsmithing</researchPrerequisite>
        </recipeMaker>
        <weaponTags>
            <li>Gun</li>
        </weaponTags>
    </ThingDef>
	
</Defs>